<Properties GitUserInfo="UsingMD" StartupConfiguration="{40B2D5B3-10CF-4E25-A51A-8F24785005BE}|acades.website">
  <MonoDevelop.Ide.ItemProperties.Acades.Website PreferredExecutionTarget="/Applications/Safari.app" />
  <MonoDevelop.Ide.ItemProperties.acades.website PreferredExecutionTarget="/Applications/Safari.app" />
  <MonoDevelop.Ide.Workbench ActiveDocument="Acades.Website/ClientApp/src/app/watermark/watermark.component.html">
    <Files>
      <File FileName="Acades.Website/ClientApp/src/app/watermark/watermark.component.html" Line="193" Column="37" />
      <File FileName="Acades.Website/ClientApp/src/app/watermark/watermark.component.ts" Line="18" Column="1" />
      <File FileName="Acades.Website/ClientApp/src/app/app.module.ts" Line="24" Column="36" />
      <File FileName="Acades.Website/ClientApp/package.json" Line="28" Column="1" />
      <File FileName="Acades.Website/ClientApp/angular.json" Line="26" Column="16" />
      <File FileName="Acades.Website/ClientApp/src/index.html" />
      <File FileName="Acades.Website/ClientApp/src/app/app.server.module.ts" Line="1" Column="1" />
    </Files>
    <Pads>
      <Pad Id="ProjectPad">
        <State name="__root__">
          <Node name="acades" expanded="True">
            <Node name="Acades.Website" expanded="True" selected="True">
              <Node name="ClientApp" expanded="True">
                <Node name="src" expanded="True">
                  <Node name="app" expanded="True">
                    <Node name="watermark" expanded="True" />
                  </Node>
                </Node>
              </Node>
              <Node name="Controllers" expanded="True" />
            </Node>
          </Node>
        </State>
      </Pad>
    </Pads>
  </MonoDevelop.Ide.Workbench>
  <MonoDevelop.Ide.DebuggingService.PinnedWatches />
  <MonoDevelop.Ide.Workspace ActiveConfiguration="Release" />
  <MonoDevelop.Ide.ItemProperties.Services.Acades.API PreferredExecutionTarget="/Applications/Safari.app" />
  <MonoDevelop.Ide.ItemProperties.Laboratory.WatermarkSamples.StampWatermakService PreferredExecutionTarget="/Applications/Safari.app" />
  <MonoDevelop.Ide.DebuggingService.Breakpoints>
    <BreakpointStore />
  </MonoDevelop.Ide.DebuggingService.Breakpoints>
  <MultiItemStartupConfigurations />
</Properties>